epiVIA/__init__.py
epiVIA/chimera.py
epiVIA/integration.py
epiVIA/report.py
epiVIA/ucsctracks.py
epiVIA/utils.py
epiVIA-1.1.2.dist-info/METADATA
epiVIA-1.1.2.dist-info/WHEEL
epiVIA-1.1.2.dist-info/entry_points.txt
epiVIA-1.1.2.dist-info/top_level.txt
epiVIA-1.1.2.dist-info/RECORD
