Metadata-Version: 2.1
Name: epiVIA
Version: 1.1.2
Summary: Virial Integration Analysis with epigenetic data
Home-page: https://github.com/wangwl/epiVIA
Author: Wenliang Wang
Author-email: wangwl.me@gmail.com
License: UNKNOWN
Platform: UNKNOWN
Classifier: Programming Language :: Python :: 3
Classifier: License :: OSI Approved :: MIT License
Classifier: Operating System :: OS Independent
Requires-Dist: pysam
Requires-Dist: pandas
Requires-Dist: biopython
Requires-Dist: requests
Requires-Dist: pybedtools
